dynamizer/__init__.py
dynamizer/_models.py
dynamizer/_stream.py
dynamizer/errors.py
dynamizer/mock.py
dynamizer-0.2.14.dist-info/LICENSE
dynamizer-0.2.14.dist-info/METADATA
dynamizer-0.2.14.dist-info/WHEEL
dynamizer-0.2.14.dist-info/RECORD
