Metadata-Version: 2.3
Name: dynamizer
Version: 0.2.14
Summary: Dynamodb model maker.
License: MIT
Author: Kevin Schiroo
Author-email: kjschiroo@gmail.com
Requires-Python: >=3.10,<4.0
Classifier: License :: OSI Approved :: MIT License
Classifier: Programming Language :: Python :: 3
Classifier: Programming Language :: Python :: 3.10
Classifier: Programming Language :: Python :: 3.11
Classifier: Programming Language :: Python :: 3.12
Classifier: Programming Language :: Python :: 3.13
Provides-Extra: mock
Requires-Dist: moto[dynamodb] (>=5.0.1,<6.0.0) ; extra == "mock"
